{
  "warning": [
    {
      "identifier": "undefined--vi-avl.2024-08-09_20-51-00-000.f.de0",
      "icon": "101",
      "isBlocked": "false",
      "future": false,
      "extent": "48.8359732365759,12.903703543693917,48.81185156579159,12.963439067183426",
      "point": "48.8359732365759,12.903703543693917",
      "startLcPosition": "27",
      "display_type": "WARNING",
      "subtitle": " Nürnberg -> Passau",
      "title": "A3 | Metten - Isarblick",
      "startTimestamp": "2024-08-09T20:51:00+02:00",
      "delayTimeValue": "4",
      "abnormalTrafficType": "QUEUING_TRAFFIC",
      "averageSpeed": "45.29999923706055",
      "coordinate": {
        "lat": 48.8359732365759,
        "long": 12.903703543693917
      },
      "description": [
        "Beginn: 09.08.24 um 20:51 Uhr",
        "Ende: 09.08.24 um 21:46 Uhr",
        "",
        "Angespannte Verkehrslage, von 09.08.2024, 20:51, bis 09.08.2024, 21:46",
        "A3: Nürnberg -> Passau, zwischen 1.6 km hinter AS Metten und 1.4 km vor Isarblick"
      ],
      "routeRecommendation": [],
      "footer": [],
      "lorryParkingFeatureIcons": [],
      "geometry": {
        "type": "LineString",
        "coordinates": [
          [
            12.903703544,
            48.835973237
          ],
          [
            12.9040197,
            48.835731201
          ],
          [
            12.9058835,
            48.834411801
          ],
          [
            12.9076187,
            48.833231301
          ],
          [
            12.9079761,
            48.832997901
          ],
          [
            12.9101031,
            48.831624801
          ],
          [
            12.9124693,
            48.830189901
          ],
          [
            12.9137905,
            48.829431601
          ],
          [
            12.9151964,
            48.828664301
          ],
          [
            12.9165901,
            48.827912201
          ],
          [
            12.9179837,
            48.827160101
          ],
          [
            12.9201494,
            48.826071001
          ],
          [
            12.9225167,
            48.824938801
          ],
          [
            12.9251462,
            48.823763701
          ],
          [
            12.9254349,
            48.823640001
          ],
          [
            12.9256075,
            48.823566001
          ],
          [
            12.9268807,
            48.823020201
          ],
          [
            12.9272949,
            48.822842601
          ],
          [
            12.9284197,
            48.822384701
          ],
          [
            12.9312244,
            48.821289601
          ],
          [
            12.9332687,
            48.820541701
          ],
          [
            12.934023,
            48.820273101
          ],
          [
            12.9360253,
            48.819588801
          ],
          [
            12.9388696,
            48.818668301
          ],
          [
            12.9410159,
            48.818027301
          ],
          [
            12.9436895,
            48.817270801
          ],
          [
            12.9447125,
            48.816999501
          ],
          [
            12.9457481,
            48.816734701
          ],
          [
            12.9473258,
            48.816330401
          ],
          [
            12.9491806,
            48.815859101
          ],
          [
            12.9503729,
            48.815551101
          ],
          [
            12.9562728,
            48.814100101
          ],
          [
            12.9588213,
            48.813387401
          ],
          [
            12.9609436,
            48.812727901
          ],
          [
            12.9630144,
            48.812012801
          ],
          [
            12.963439067,
            48.811851566
          ]
        ]
      }
    },
    {
      "identifier": "undefined--vi-avl.2024-08-09_11-08-40-000.f_008.de0",
      "icon": "101",
      "isBlocked": "false",
      "future": false,
      "extent": "50.58785320075146,7.457842273198103,50.61793945631461,7.411899481504633",
      "point": "50.58785320075146,7.457842273198103",
      "startLcPosition": "193",
      "display_type": "WARNING",
      "subtitle": " Frankfurt -> Köln",
      "title": "A3 | Epgert - Hambitz",
      "startTimestamp": "2024-08-09T11:08:40+02:00",
      "delayTimeValue": "7",
      "abnormalTrafficType": "STATIONARY_TRAFFIC",
      "averageSpeed": "27.899999618530273",
      "coordinate": {
        "lat": 50.58785320075146,
        "long": 7.457842273198103
      },
      "description": [
        "Beginn: 09.08.24 um 11:08 Uhr",
        "Ende: 09.08.24 um 21:33 Uhr",
        "",
        "Angespannte Verkehrslage, von 09.08.2024, 11:08, bis 09.08.2024, 21:33",
        "A3: Frankfurt -> Köln, zwischen 1.8 km hinter Epgert und 4.3 km vor Hambitz"
      ],
      "routeRecommendation": [],
      "footer": [],
      "lorryParkingFeatureIcons": [],
      "geometry": {
        "type": "LineString",
        "coordinates": [
          [
            7.457842273,
            50.587853201
          ],
          [
            7.4547576,
            50.589744701
          ],
          [
            7.4532286,
            50.590698701
          ],
          [
            7.4488557,
            50.593395001
          ],
          [
            7.4466135,
            50.594779301
          ],
          [
            7.4448556,
            50.595859601
          ],
          [
            7.4443995,
            50.596119501
          ],
          [
            7.4438818,
            50.596387501
          ],
          [
            7.4433867,
            50.596608301
          ],
          [
            7.4428483,
            50.596826601
          ],
          [
            7.4424157,
            50.596986301
          ],
          [
            7.4417507,
            50.597200501
          ],
          [
            7.4408757,
            50.597420301
          ],
          [
            7.4395139,
            50.597738701
          ],
          [
            7.4380722,
            50.598072301
          ],
          [
            7.4370899,
            50.598313401
          ],
          [
            7.4362429,
            50.598569101
          ],
          [
            7.4354957,
            50.598858201
          ],
          [
            7.4347733,
            50.599171801
          ],
          [
            7.4341996,
            50.599473201
          ],
          [
            7.4337586,
            50.599750501
          ],
          [
            7.4333511,
            50.600001801
          ],
          [
            7.4327407,
            50.600445501
          ],
          [
            7.4322006,
            50.600933801
          ],
          [
            7.4317009,
            50.601443101
          ],
          [
            7.4314245,
            50.601810701
          ],
          [
            7.4311374,
            50.602224501
          ],
          [
            7.4307686,
            50.602930701
          ],
          [
            7.4306533,
            50.603188201
          ],
          [
            7.4305587,
            50.603370501
          ],
          [
            7.4304749,
            50.603531901
          ],
          [
            7.4300095,
            50.604452101
          ],
          [
            7.4297256,
            50.605059501
          ],
          [
            7.4292551,
            50.606137301
          ],
          [
            7.4283491,
            50.608034901
          ],
          [
            7.4279131,
            50.608953001
          ],
          [
            7.4271633,
            50.610538201
          ],
          [
            7.4269813,
            50.610888201
          ],
          [
            7.4267056,
            50.611367901
          ],
          [
            7.4264851,
            50.611700501
          ],
          [
            7.4261014,
            50.612197901
          ],
          [
            7.4255748,
            50.612776201
          ],
          [
            7.4251592,
            50.613133301
          ],
          [
            7.4246415,
            50.613540001
          ],
          [
            7.423983,
            50.613987701
          ],
          [
            7.4232366,
            50.614412901
          ],
          [
            7.4222088,
            50.614865901
          ],
          [
            7.4214898,
            50.615136401
          ],
          [
            7.4205521,
            50.615437401
          ],
          [
            7.4170648,
            50.616450801
          ],
          [
            7.4146955,
            50.617133401
          ],
          [
            7.4142786,
            50.617249501
          ],
          [
            7.411899482,
            50.617939456
          ]
        ]
      }
    }
  ]
}
