{
  "warning": [
    {
      "identifier": "undefined--vi-avl.2025-08-13_08-20-29-000.f.de0",
      "icon": "101",
      "isBlocked": "false",
      "future": false,
      "extent": "48.42320533145101,13.391148805346562,48.45766005208211,13.375637800206764",
      "point": "48.42320533145101,13.391148805346562",
      "startLcPosition": "1",
      "display_type": "WARNING",
      "subtitle": " Linz -> Passau",
      "title": "A3 | Neuhaus am Inn - Rottal-Ost",
      "startTimestamp": "2025-08-13T08:20:29+02:00",
      "delayTimeValue": "16",
      "abnormalTrafficType": "STATIONARY_TRAFFIC",
      "averageSpeed": "12.199999809265137",
      "coordinate": {
        "lat": 48.42320533145101,
        "long": 13.391148805346562
      },
      "description": [
        "Beginn: 13.08.25 um 08:20 Uhr",
        "",
        "Angespannte Verkehrslage, seit 13.08.2025, 08:20",
        "A3: Linz -> Passau, zwischen 2.3 km hinter Neuhaus am Inn und 0.2 km vor Rottal-Ost",
        "",
        "Im Stillstand",
        "Reisezeitverlust: 16 Minuten",
        "Durchschnittsgeschwindigkeit: 12 km/h"
      ],
      "routeRecommendation": [],
      "footer": [],
      "lorryParkingFeatureIcons": [],
      "geometry": {
        "type": "LineString",
        "coordinates": [
          [
            13.391148805,
            48.423205331
          ],
          [
            13.390287,
            48.423664201
          ],
          [
            13.3862613,
            48.426119001
          ],
          [
            13.3827277,
            48.428769701
          ],
          [
            13.3819918,
            48.429419501
          ],
          [
            13.3810067,
            48.430345901
          ],
          [
            13.3803579,
            48.431017901
          ],
          [
            13.3797629,
            48.431680701
          ],
          [
            13.3789632,
            48.432664301
          ],
          [
            13.3786073,
            48.433154401
          ],
          [
            13.3783558,
            48.433503001
          ],
          [
            13.3776767,
            48.434581201
          ],
          [
            13.3774526,
            48.434978801
          ],
          [
            13.3772285,
            48.435388801
          ],
          [
            13.3769736,
            48.435890001
          ],
          [
            13.3767686,
            48.436328701
          ],
          [
            13.3765049,
            48.436935601
          ],
          [
            13.3763902,
            48.437252401
          ],
          [
            13.3761825,
            48.437808401
          ],
          [
            13.375996,
            48.438382101
          ],
          [
            13.3759329,
            48.438610901
          ],
          [
            13.3758669,
            48.438842201
          ],
          [
            13.3757956,
            48.439115101
          ],
          [
            13.3756766,
            48.439617301
          ],
          [
            13.3754824,
            48.440630101
          ],
          [
            13.3753399,
            48.442335601
          ],
          [
            13.375356,
            48.443530001
          ],
          [
            13.3754472,
            48.445064001
          ],
          [
            13.3755353,
            48.445793701
          ],
          [
            13.3756414,
            48.446647001
          ],
          [
            13.3759979,
            48.449662601
          ],
          [
            13.3760549,
            48.450436301
          ],
          [
            13.3760854,
            48.450850501
          ],
          [
            13.3761194,
            48.451589101
          ],
          [
            13.376141,
            48.452878801
          ],
          [
            13.3761295,
            48.453277701
          ],
          [
            13.3761168,
            48.453469301
          ],
          [
            13.3760568,
            48.454371001
          ],
          [
            13.3760373,
            48.454617101
          ],
          [
            13.3760053,
            48.455020001
          ],
          [
            13.3759271,
            48.455742801
          ],
          [
            13.3758284,
            48.456535901
          ],
          [
            13.3757258,
            48.457205601
          ],
          [
            13.3756409,
            48.457642201
          ],
          [
            13.3756378,
            48.457660052
          ]
        ]
      }
    },
    {
      "identifier": "undefined--vi-avl.2025-08-13_08-22-52-000.f_001.de0",
      "icon": "101",
      "isBlocked": "false",
      "future": false,
      "extent": "48.423194106031396,13.391169887525857,48.423194106031396,13.391169887525857",
      "point": "48.423194106031396,13.391169887525857",
      "startLcPosition": "2",
      "display_type": "WARNING",
      "subtitle": " Linz -> Passau",
      "title": "A3 | Pocking - Pocking",
      "startTimestamp": "2025-08-13T11:11:53+02:00",
      "abnormalTrafficType": "STATIONARY_TRAFFIC",
      "averageSpeed": "12",
      "coordinate": {
        "lat": 48.423194106031396,
        "long": 13.391169887525857
      },
      "description": [
        "Beginn: 13.08.25 um 11:11 Uhr",
        "",
        "Angespannte Verkehrslage, seit 13.08.2025, 11:11",
        "A3: Linz -> Passau, 1.7 km vor AS Pocking, aus Richtung Neuhaus am Inn",
        "",
        "Im Stillstand",
        "Durchschnittsgeschwindigkeit: 12 km/h"
      ],
      "routeRecommendation": [],
      "footer": [],
      "lorryParkingFeatureIcons": []
    },
    {
      "identifier": "undefined--vi-avl.2025-08-13_10-29-03-000.f.de0",
      "icon": "101",
      "isBlocked": "false",
      "future": false,
      "extent": "49.314358031597926,11.48462071789076,49.323904722413026,11.461153459092007",
      "point": "49.314358031597926,11.48462071789076",
      "startLcPosition": "69",
      "display_type": "WARNING",
      "subtitle": " Passau -> Nürnberg",
      "title": "A3 | Wolfstein - Eichenäcker",
      "startTimestamp": "2025-08-13T10:29:03+02:00",
      "delayTimeValue": "4",
      "abnormalTrafficType": "STATIONARY_TRAFFIC",
      "averageSpeed": "21.5",
      "coordinate": {
        "lat": 49.314358031597926,
        "long": 11.48462071789076
      },
      "description": [
        "Beginn: 13.08.25 um 10:29 Uhr",
        "",
        "Angespannte Verkehrslage, seit 13.08.2025, 10:29",
        "A3: Passau -> Nürnberg, zwischen 0.4 km hinter Wolfstein und 4.0 km vor Eichenäcker",
        "",
        "Im Stillstand",
        "Reisezeitverlust: 4 Minuten",
        "Durchschnittsgeschwindigkeit: 21 km/h"
      ],
      "routeRecommendation": [],
      "footer": [],
      "lorryParkingFeatureIcons": [],
      "geometry": {
        "type": "LineString",
        "coordinates": [
          [
            11.484620718,
            49.314358032
          ],
          [
            11.4845809,
            49.314362301
          ],
          [
            11.4840153,
            49.314446901
          ],
          [
            11.4823907,
            49.314715501
          ],
          [
            11.4810302,
            49.314988201
          ],
          [
            11.4791909,
            49.315401401
          ],
          [
            11.4783688,
            49.315615301
          ],
          [
            11.477651,
            49.315807601
          ],
          [
            11.4767734,
            49.316059601
          ],
          [
            11.4760114,
            49.316290201
          ],
          [
            11.4752859,
            49.316510601
          ],
          [
            11.474475,
            49.316788901
          ],
          [
            11.4733824,
            49.317172401
          ],
          [
            11.4711259,
            49.318076601
          ],
          [
            11.4701316,
            49.318514601
          ],
          [
            11.4686372,
            49.319221201
          ],
          [
            11.4675108,
            49.319808501
          ],
          [
            11.46633,
            49.320475701
          ],
          [
            11.4659545,
            49.320691301
          ],
          [
            11.4655075,
            49.320965901
          ],
          [
            11.4646027,
            49.321511701
          ],
          [
            11.4628559,
            49.322643101
          ],
          [
            11.4621315,
            49.323157901
          ],
          [
            11.4614425,
            49.323678701
          ],
          [
            11.461153459,
            49.323904722
          ]
        ]
      }
    },
    {
      "identifier": "undefined--vi-avl.2025-08-13_10-59-37-000.f_007.de0",
      "icon": "101",
      "isBlocked": "false",
      "future": false,
      "extent": "49.314344934667716,11.484742865038593,49.314344934667716,11.484742865038593",
      "point": "49.314344934667716,11.484742865038593",
      "startLcPosition": "70",
      "display_type": "WARNING",
      "subtitle": " Passau -> Nürnberg",
      "title": "A3 | Neumarkt/Oberpfalz - Neumarkt/Oberpfalz",
      "startTimestamp": "2025-08-13T11:11:53+02:00",
      "abnormalTrafficType": "STATIONARY_TRAFFIC",
      "averageSpeed": "21",
      "coordinate": {
        "lat": 49.314344934667716,
        "long": 11.484742865038593
      },
      "description": [
        "Beginn: 13.08.25 um 11:11 Uhr",
        "",
        "Angespannte Verkehrslage, seit 13.08.2025, 11:11",
        "A3: Passau -> Nürnberg, 0.7 km vor AS Neumarkt/Oberpfalz, aus Richtung Wolfstein",
        "",
        "Im Stillstand",
        "Durchschnittsgeschwindigkeit: 21 km/h"
      ],
      "routeRecommendation": [],
      "footer": [],
      "lorryParkingFeatureIcons": []
    },
    {
      "identifier": "undefined--vi-unf.2025-08-13_10-10-27-000.f_007.de0",
      "icon": "101",
      "isBlocked": "false",
      "future": false,
      "extent": "49.37739325403459,11.357325912472207,49.376700456675984,11.375532983028457",
      "point": "49.37739325403459,11.357325912472207",
      "startLcPosition": "74",
      "display_type": "WARNING",
      "subtitle": " Nürnberg -> Passau",
      "title": "A3 | Altdorf/Burgthann - Klosterblick",
      "startTimestamp": "2025-08-13T10:10:27+02:00",
      "coordinate": {
        "lat": 49.37739325403459,
        "long": 11.357325912472207
      },
      "description": [
        "Beginn: 13.08.25 um 10:10 Uhr",
        "",
        "Unfall, seit 13.08.2025, 10:10",
        "A3: Nürnberg -> Passau, zwischen 1.3 km hinter AS Altdorf/Burgthann und 2.9 km vor Klosterblick"
      ],
      "routeRecommendation": [],
      "footer": [],
      "lorryParkingFeatureIcons": [],
      "geometry": {
        "type": "LineString",
        "coordinates": [
          [
            11.357325912,
            49.377393254
          ],
          [
            11.359152,
            49.377295001
          ],
          [
            11.3601848,
            49.377280501
          ],
          [
            11.3609404,
            49.377282501
          ],
          [
            11.3615165,
            49.377290301
          ],
          [
            11.3624584,
            49.377316801
          ],
          [
            11.3649454,
            49.377403501
          ],
          [
            11.3660478,
            49.377432501
          ],
          [
            11.3673023,
            49.377438001
          ],
          [
            11.3682857,
            49.377422101
          ],
          [
            11.369606,
            49.377368001
          ],
          [
            11.370744,
            49.377298501
          ],
          [
            11.3715356,
            49.377235501
          ],
          [
            11.3728087,
            49.377113201
          ],
          [
            11.3732048,
            49.377067801
          ],
          [
            11.3736677,
            49.377010901
          ],
          [
            11.374476,
            49.376884201
          ],
          [
            11.3753372,
            49.376738001
          ],
          [
            11.375532983,
            49.376700457
          ]
        ]
      }
    },
    {
      "identifier": "undefined--vi-hind.2025-08-13_10-10-27-000.f_005.de0",
      "icon": "101",
      "isBlocked": "false",
      "future": false,
      "extent": "49.39940430094358,11.304096300006345,49.361355500943716,11.425877200008168",
      "point": "49.39940430094358,11.304096300006345",
      "startLcPosition": "76",
      "display_type": "WARNING",
      "subtitle": " Nürnberg -> Passau",
      "title": "A3 | Altdorf - Eichenäcker",
      "startTimestamp": "2025-08-13T10:10:27+02:00",
      "coordinate": {
        "lat": 49.39940430094358,
        "long": 11.304096300006345
      },
      "description": [
        "Beginn: 13.08.25 um 10:10 Uhr",
        "",
        "Fahrzeug-Hindernis, seit 13.08.2025, 10:10",
        "A3: Nürnberg -> Passau, zwischen 0.6 km hinter AK Altdorf und 1.0 km vor Eichenäcker",
        "Gefahr durch ein defektes Fahrzeug auf der Fahrbahn"
      ],
      "routeRecommendation": [],
      "footer": [],
      "lorryParkingFeatureIcons": [],
      "geometry": {
        "type": "LineString",
        "coordinates": [
          [
            11.3040963,
            49.399404301
          ],
          [
            11.3052753,
            49.398115601
          ],
          [
            11.3054057,
            49.397969401
          ],
          [
            11.3059818,
            49.397330101
          ],
          [
            11.3065072,
            49.396741801
          ],
          [
            11.3069952,
            49.396204201
          ],
          [
            11.3080709,
            49.395057501
          ],
          [
            11.3090498,
            49.394046001
          ],
          [
            11.3094082,
            49.393699301
          ],
          [
            11.3101008,
            49.393067401
          ],
          [
            11.3117628,
            49.391676801
          ],
          [
            11.3127611,
            49.390868101
          ],
          [
            11.3138219,
            49.390077801
          ],
          [
            11.3140753,
            49.389903901
          ],
          [
            11.3148036,
            49.389413001
          ],
          [
            11.3153792,
            49.389058901
          ],
          [
            11.3163859,
            49.388451501
          ],
          [
            11.3173505,
            49.387934901
          ],
          [
            11.3183598,
            49.387407901
          ],
          [
            11.3194532,
            49.386886101
          ],
          [
            11.32072,
            49.386335101
          ],
          [
            11.321774,
            49.385917701
          ],
          [
            11.322904,
            49.385507801
          ],
          [
            11.3244109,
            49.385020101
          ],
          [
            11.3250956,
            49.384819601
          ],
          [
            11.3256974,
            49.384639101
          ],
          [
            11.3260552,
            49.384540401
          ],
          [
            11.32649,
            49.384431701
          ],
          [
            11.3267447,
            49.384367701
          ],
          [
            11.3273986,
            49.384206501
          ],
          [
            11.328428,
            49.383973301
          ],
          [
            11.3287728,
            49.383899401
          ],
          [
            11.3292724,
            49.383803901
          ],
          [
            11.3299941,
            49.383659401
          ],
          [
            11.3310161,
            49.383474001
          ],
          [
            11.3316544,
            49.383365001
          ],
          [
            11.3330919,
            49.383118701
          ],
          [
            11.3345119,
            49.382862201
          ],
          [
            11.335431,
            49.382690201
          ],
          [
            11.3359823,
            49.382580801
          ],
          [
            11.3371828,
            49.382318401
          ],
          [
            11.3379001,
            49.382167701
          ],
          [
            11.3398912,
            49.381678901
          ],
          [
            11.3401781,
            49.381600901
          ],
          [
            11.34037,
            49.381549201
          ],
          [
            11.3416232,
            49.381211401
          ],
          [
            11.3422829,
            49.381028501
          ],
          [
            11.3427193,
            49.380896201
          ],
          [
            11.343339,
            49.380706801
          ],
          [
            11.3438844,
            49.380533401
          ],
          [
            11.3442255,
            49.380422701
          ],
          [
            11.3446139,
            49.380292501
          ],
          [
            11.3468315,
            49.379560101
          ],
          [
            11.3474988,
            49.379348901
          ],
          [
            11.3493406,
            49.378794301
          ],
          [
            11.3507152,
            49.378418301
          ],
          [
            11.3520202,
            49.378123001
          ],
          [
            11.3525929,
            49.378013101
          ],
          [
            11.3534987,
            49.377850301
          ],
          [
            11.3545784,
            49.377683301
          ],
          [
            11.3559365,
            49.377513101
          ],
          [
            11.3570964,
            49.377405601
          ],
          [
            11.359152,
            49.377295001
          ],
          [
            11.3601848,
            49.377280501
          ],
          [
            11.3609404,
            49.377282501
          ],
          [
            11.3615165,
            49.377290301
          ],
          [
            11.3624584,
            49.377316801
          ],
          [
            11.3649454,
            49.377403501
          ],
          [
            11.3660478,
            49.377432501
          ],
          [
            11.3673023,
            49.377438001
          ],
          [
            11.3682857,
            49.377422101
          ],
          [
            11.369606,
            49.377368001
          ],
          [
            11.370744,
            49.377298501
          ],
          [
            11.3715356,
            49.377235501
          ],
          [
            11.3728087,
            49.377113201
          ],
          [
            11.3732048,
            49.377067801
          ],
          [
            11.3736677,
            49.377010901
          ],
          [
            11.374476,
            49.376884201
          ],
          [
            11.3753372,
            49.376738001
          ],
          [
            11.3763723,
            49.376539501
          ],
          [
            11.3783722,
            49.376092701
          ],
          [
            11.379874,
            49.375681301
          ],
          [
            11.38136,
            49.375161501
          ],
          [
            11.3818206,
            49.374999701
          ],
          [
            11.3837357,
            49.374261801
          ],
          [
            11.3871142,
            49.372757901
          ],
          [
            11.3907807,
            49.371121401
          ],
          [
            11.391666,
            49.370771701
          ],
          [
            11.3927893,
            49.370308201
          ],
          [
            11.3934962,
            49.370032401
          ],
          [
            11.3940866,
            49.369796101
          ],
          [
            11.3947241,
            49.369571001
          ],
          [
            11.3981516,
            49.368454501
          ],
          [
            11.4025473,
            49.367278701
          ],
          [
            11.4046996,
            49.366776801
          ],
          [
            11.4062947,
            49.366441001
          ],
          [
            11.4128113,
            49.364984201
          ],
          [
            11.416445,
            49.364104701
          ],
          [
            11.4183518,
            49.363621001
          ],
          [
            11.4195636,
            49.363309401
          ],
          [
            11.4199266,
            49.363205901
          ],
          [
            11.4208545,
            49.362945901
          ],
          [
            11.4217064,
            49.362709801
          ],
          [
            11.422202,
            49.362564201
          ],
          [
            11.4232142,
            49.362260101
          ],
          [
            11.4237672,
            49.362081001
          ],
          [
            11.424568,
            49.361815801
          ],
          [
            11.4250147,
            49.361659501
          ],
          [
            11.4255716,
            49.361466501
          ],
          [
            11.4258772,
            49.361355501
          ]
        ]
      }
    },
    {
      "identifier": "undefined--vi-avl.2025-08-13_10-54-03-000.f_015.de0",
      "icon": "101",
      "isBlocked": "false",
      "future": false,
      "extent": "49.420675938282386,11.279228799749495,49.420675938282386,11.279228799749495",
      "point": "49.420675938282386,11.279228799749495",
      "startLcPosition": "76",
      "display_type": "WARNING",
      "subtitle": " Nürnberg -> Passau",
      "title": "A3 | Altdorf - Altdorf",
      "startTimestamp": "2025-08-13T11:11:53+02:00",
      "abnormalTrafficType": "STATIONARY_TRAFFIC",
      "averageSpeed": "9",
      "coordinate": {
        "lat": 49.420675938282386,
        "long": 11.279228799749495
      },
      "description": [
        "Beginn: 13.08.25 um 11:11 Uhr",
        "",
        "Angespannte Verkehrslage, seit 13.08.2025, 11:11",
        "A3: Nürnberg -> Passau, 2.3 km vor AK Altdorf, aus Richtung Fuchsmühle",
        "",
        "Im Stillstand",
        "Durchschnittsgeschwindigkeit: 9 km/h"
      ],
      "routeRecommendation": [],
      "footer": [],
      "lorryParkingFeatureIcons": []
    },
    {
      "identifier": "undefined--vi-zus.2025-08-13_10-52-47-000.f_001.de0",
      "icon": "101",
      "isBlocked": "false",
      "future": false,
      "extent": "49.420675938282386,11.279228799749495,49.377412439674195,11.36528515225184",
      "point": "49.420675938282386,11.279228799749495",
      "startLcPosition": "77",
      "display_type": "WARNING",
      "subtitle": " Nürnberg -> Passau",
      "title": "A3 | Fuchsmühle - Klosterblick",
      "startTimestamp": "2025-08-13T10:52:47+02:00",
      "delayTimeValue": "52",
      "abnormalTrafficType": "STATIONARY_TRAFFIC",
      "averageSpeed": "8.899999618530273",
      "coordinate": {
        "lat": 49.420675938282386,
        "long": 11.279228799749495
      },
      "description": [
        "Beginn: 13.08.25 um 10:52 Uhr",
        "",
        "Zusammengesetzte Verkehrsinformation, seit 13.08.2025, 10:52",
        "A3: Nürnberg -> Passau, zwischen 1.6 km hinter Fuchsmühle und 3.6 km vor Klosterblick",
        "",
        "Im Stillstand",
        "Reisezeitverlust: 52 Minuten",
        "Durchschnittsgeschwindigkeit: 8 km/h",
        "",
        "Gefahr durch ein defektes Fahrzeugs auf der Fahrbahn"
      ],
      "routeRecommendation": [],
      "footer": [],
      "lorryParkingFeatureIcons": [],
      "geometry": {
        "type": "LineString",
        "coordinates": [
          [
            11.2792288,
            49.420675938
          ],
          [
            11.2798262,
            49.419981301
          ],
          [
            11.2804443,
            49.419277301
          ],
          [
            11.2813507,
            49.418282501
          ],
          [
            11.2824437,
            49.417150501
          ],
          [
            11.2836725,
            49.415941101
          ],
          [
            11.284608,
            49.415050301
          ],
          [
            11.2851194,
            49.414574101
          ],
          [
            11.2863129,
            49.413503401
          ],
          [
            11.2877086,
            49.412318101
          ],
          [
            11.2889919,
            49.411282601
          ],
          [
            11.2903926,
            49.410178201
          ],
          [
            11.2908765,
            49.409817901
          ],
          [
            11.2915224,
            49.409337301
          ],
          [
            11.2916835,
            49.409220801
          ],
          [
            11.2922331,
            49.408813001
          ],
          [
            11.292747,
            49.408451201
          ],
          [
            11.2934405,
            49.407965101
          ],
          [
            11.2944555,
            49.407262201
          ],
          [
            11.2972652,
            49.405351701
          ],
          [
            11.2993041,
            49.403826501
          ],
          [
            11.300816,
            49.402593001
          ],
          [
            11.3018433,
            49.401681901
          ],
          [
            11.3030165,
            49.400544201
          ],
          [
            11.3033278,
            49.400233501
          ],
          [
            11.303961,
            49.399559701
          ],
          [
            11.3040963,
            49.399404301
          ],
          [
            11.3052753,
            49.398115601
          ],
          [
            11.3054057,
            49.397969401
          ],
          [
            11.3059818,
            49.397330101
          ],
          [
            11.3065072,
            49.396741801
          ],
          [
            11.3069952,
            49.396204201
          ],
          [
            11.3080709,
            49.395057501
          ],
          [
            11.3090498,
            49.394046001
          ],
          [
            11.3094082,
            49.393699301
          ],
          [
            11.3101008,
            49.393067401
          ],
          [
            11.3117628,
            49.391676801
          ],
          [
            11.3127611,
            49.390868101
          ],
          [
            11.3138219,
            49.390077801
          ],
          [
            11.3140753,
            49.389903901
          ],
          [
            11.3148036,
            49.389413001
          ],
          [
            11.3153792,
            49.389058901
          ],
          [
            11.3163859,
            49.388451501
          ],
          [
            11.3173505,
            49.387934901
          ],
          [
            11.3183598,
            49.387407901
          ],
          [
            11.3194532,
            49.386886101
          ],
          [
            11.32072,
            49.386335101
          ],
          [
            11.321774,
            49.385917701
          ],
          [
            11.322904,
            49.385507801
          ],
          [
            11.3244109,
            49.385020101
          ],
          [
            11.3250956,
            49.384819601
          ],
          [
            11.3256974,
            49.384639101
          ],
          [
            11.3260552,
            49.384540401
          ],
          [
            11.32649,
            49.384431701
          ],
          [
            11.3267447,
            49.384367701
          ],
          [
            11.3273986,
            49.384206501
          ],
          [
            11.328428,
            49.383973301
          ],
          [
            11.3287728,
            49.383899401
          ],
          [
            11.3292724,
            49.383803901
          ],
          [
            11.3299941,
            49.383659401
          ],
          [
            11.3310161,
            49.383474001
          ],
          [
            11.3316544,
            49.383365001
          ],
          [
            11.3330919,
            49.383118701
          ],
          [
            11.3345119,
            49.382862201
          ],
          [
            11.335431,
            49.382690201
          ],
          [
            11.3359823,
            49.382580801
          ],
          [
            11.3371828,
            49.382318401
          ],
          [
            11.3379001,
            49.382167701
          ],
          [
            11.3398912,
            49.381678901
          ],
          [
            11.3401781,
            49.381600901
          ],
          [
            11.34037,
            49.381549201
          ],
          [
            11.3416232,
            49.381211401
          ],
          [
            11.3422829,
            49.381028501
          ],
          [
            11.3427193,
            49.380896201
          ],
          [
            11.343339,
            49.380706801
          ],
          [
            11.3438844,
            49.380533401
          ],
          [
            11.3442255,
            49.380422701
          ],
          [
            11.3446139,
            49.380292501
          ],
          [
            11.3468315,
            49.379560101
          ],
          [
            11.3474988,
            49.379348901
          ],
          [
            11.3493406,
            49.378794301
          ],
          [
            11.3507152,
            49.378418301
          ],
          [
            11.3520202,
            49.378123001
          ],
          [
            11.3525929,
            49.378013101
          ],
          [
            11.3534987,
            49.377850301
          ],
          [
            11.3545784,
            49.377683301
          ],
          [
            11.3559365,
            49.377513101
          ],
          [
            11.3570964,
            49.377405601
          ],
          [
            11.359152,
            49.377295001
          ],
          [
            11.3601848,
            49.377280501
          ],
          [
            11.3609404,
            49.377282501
          ],
          [
            11.3615165,
            49.377290301
          ],
          [
            11.3624584,
            49.377316801
          ],
          [
            11.3649454,
            49.377403501
          ],
          [
            11.365285152,
            49.37741244
          ]
        ]
      }
    },
    {
      "identifier": "undefined--vi-avl.2025-08-13_10-17-33-000.f.de0",
      "icon": "101",
      "isBlocked": "false",
      "future": false,
      "extent": "49.621471586807004,10.920728862417086,49.65740161175014,10.895326925152364",
      "point": "49.621471586807004,10.920728862417086",
      "startLcPosition": "88",
      "display_type": "WARNING",
      "subtitle": " Nürnberg -> Würzburg",
      "title": "A3 | Kleinauweiher - Geierbusch",
      "startTimestamp": "2025-08-13T10:17:33+02:00",
      "delayTimeValue": "2",
      "abnormalTrafficType": "SLOW_TRAFFIC",
      "averageSpeed": "52.20000076293945",
      "coordinate": {
        "lat": 49.621471586807004,
        "long": 10.920728862417086
      },
      "description": [
        "Beginn: 13.08.25 um 10:17 Uhr",
        "",
        "Angespannte Verkehrslage, seit 13.08.2025, 10:17",
        "A3: Nürnberg -> Würzburg, zwischen 1.9 km hinter Kleinauweiher und 0.1 km vor Geierbusch",
        "",
        "Langsamer Verkehr",
        "Reisezeitverlust: 2 Minuten",
        "Durchschnittsgeschwindigkeit: 52 km/h"
      ],
      "routeRecommendation": [],
      "footer": [],
      "lorryParkingFeatureIcons": [],
      "geometry": {
        "type": "LineString",
        "coordinates": [
          [
            10.920728862,
            49.621471587
          ],
          [
            10.9204523,
            49.622116001
          ],
          [
            10.9201752,
            49.622794401
          ],
          [
            10.9199867,
            49.623334101
          ],
          [
            10.9197405,
            49.624082701
          ],
          [
            10.9195952,
            49.624567401
          ],
          [
            10.9195199,
            49.624822701
          ],
          [
            10.9193922,
            49.625242801
          ],
          [
            10.9189744,
            49.626783801
          ],
          [
            10.9188729,
            49.627144301
          ],
          [
            10.9185945,
            49.628188701
          ],
          [
            10.9185747,
            49.628253101
          ],
          [
            10.9183405,
            49.629106601
          ],
          [
            10.9181792,
            49.629615601
          ],
          [
            10.9178254,
            49.630626501
          ],
          [
            10.9174535,
            49.631705801
          ],
          [
            10.9174102,
            49.631824601
          ],
          [
            10.9173422,
            49.632010801
          ],
          [
            10.9168194,
            49.633292601
          ],
          [
            10.9162848,
            49.634416901
          ],
          [
            10.9156824,
            49.635555901
          ],
          [
            10.9150722,
            49.636598701
          ],
          [
            10.9145319,
            49.637440501
          ],
          [
            10.9138195,
            49.638464701
          ],
          [
            10.9134059,
            49.639029801
          ],
          [
            10.9129698,
            49.639595901
          ],
          [
            10.9117802,
            49.641044901
          ],
          [
            10.9105866,
            49.642347001
          ],
          [
            10.9103551,
            49.642585201
          ],
          [
            10.9094199,
            49.643503601
          ],
          [
            10.9086893,
            49.644191701
          ],
          [
            10.9082665,
            49.644565401
          ],
          [
            10.9072956,
            49.645401301
          ],
          [
            10.9063584,
            49.646178001
          ],
          [
            10.906214,
            49.646295301
          ],
          [
            10.9045261,
            49.647651501
          ],
          [
            10.9034355,
            49.648568501
          ],
          [
            10.90189,
            49.649969101
          ],
          [
            10.9004535,
            49.651415501
          ],
          [
            10.8996641,
            49.652273101
          ],
          [
            10.8983482,
            49.653813901
          ],
          [
            10.8970654,
            49.655386001
          ],
          [
            10.8962795,
            49.656326101
          ],
          [
            10.8958447,
            49.656846301
          ],
          [
            10.895326925,
            49.657401612
          ]
        ]
      }
    },
    {
      "identifier": "undefined--vi-hind.2025-08-13_11-11-53-000.f.de0",
      "icon": "101",
      "isBlocked": "false",
      "future": false,
      "extent": "50.05892450291471,8.887317581902188,50.05892450291471,8.887317581902188",
      "point": "50.05892450291471,8.887317581902188",
      "startLcPosition": "155",
      "display_type": "WARNING",
      "subtitle": " Würzburg -> Frankfurt",
      "title": "A3 | Hanau - Obertshausen",
      "startTimestamp": "2025-08-13T11:11:53+02:00",
      "coordinate": {
        "lat": 50.05892450291471,
        "long": 8.887317581902188
      },
      "description": [
        "Beginn: 13.08.25 um 11:11 Uhr",
        "",
        "Fahrzeug-Hindernis, seit 13.08.2025, 11:11",
        "A3: Würzburg -> Frankfurt, zwischen 0.3 km hinter AS Hanau und 4.4 km vor AS Obertshausen",
        "Gefahr durch ein defektes Fahrzeug auf der Fahrbahn"
      ],
      "routeRecommendation": [],
      "footer": [],
      "lorryParkingFeatureIcons": []
    },
    {
      "identifier": "undefined--vi-hind.2025-08-13_10-53-24-000.f_002.de0",
      "icon": "101",
      "isBlocked": "false",
      "future": false,
      "extent": "50.05781860130018,8.895754590184557,50.027767500941025,8.94077459999998",
      "point": "50.05781860130018,8.895754590184557",
      "startLcPosition": "155",
      "display_type": "WARNING",
      "subtitle": " Frankfurt -> Würzburg",
      "title": "A3 | Hanau - Mainhausen",
      "startTimestamp": "2025-08-13T10:53:24+02:00",
      "coordinate": {
        "lat": 50.05781860130018,
        "long": 8.895754590184557
      },
      "description": [
        "Beginn: 13.08.25 um 10:53 Uhr",
        "",
        "Hindernis, seit 13.08.2025, 10:53",
        "A3: Frankfurt -> Würzburg, zwischen 0.3 km hinter AS Hanau und 4.7 km vor Mainhausen",
        "",
        "Gefahr durch Gegenstände auf der Fahrbahn"
      ],
      "routeRecommendation": [],
      "footer": [],
      "lorryParkingFeatureIcons": [],
      "geometry": {
        "type": "LineString",
        "coordinates": [
          [
            8.89575459,
            50.057818601
          ],
          [
            8.8972019,
            50.057613301
          ],
          [
            8.8986447,
            50.057392601
          ],
          [
            8.8992345,
            50.057293801
          ],
          [
            8.9003172,
            50.057112501
          ],
          [
            8.9015069,
            50.056900801
          ],
          [
            8.9022472,
            50.056761601
          ],
          [
            8.9033514,
            50.056546601
          ],
          [
            8.9044618,
            50.056315701
          ],
          [
            8.9051649,
            50.056165901
          ],
          [
            8.9058665,
            50.056010701
          ],
          [
            8.9072752,
            50.055681201
          ],
          [
            8.9086521,
            50.055338901
          ],
          [
            8.909814,
            50.055031501
          ],
          [
            8.9109499,
            50.054712001
          ],
          [
            8.9116302,
            50.054513001
          ],
          [
            8.9131021,
            50.054060101
          ],
          [
            8.9144253,
            50.053623101
          ],
          [
            8.9155215,
            50.053235701
          ],
          [
            8.9170209,
            50.052679201
          ],
          [
            8.9181202,
            50.052234001
          ],
          [
            8.9184903,
            50.052084101
          ],
          [
            8.9205411,
            50.051177201
          ],
          [
            8.9225103,
            50.050206601
          ],
          [
            8.9236562,
            50.049588501
          ],
          [
            8.9243968,
            50.049164401
          ],
          [
            8.9255688,
            50.048447701
          ],
          [
            8.9256841,
            50.048375101
          ],
          [
            8.9271466,
            50.047402701
          ],
          [
            8.9282976,
            50.046557001
          ],
          [
            8.929533,
            50.045554501
          ],
          [
            8.9298394,
            50.045276001
          ],
          [
            8.930682,
            50.044509901
          ],
          [
            8.931358,
            50.043840001
          ],
          [
            8.9319562,
            50.043199701
          ],
          [
            8.9330196,
            50.041929401
          ],
          [
            8.9339617,
            50.040626601
          ],
          [
            8.9347962,
            50.039287601
          ],
          [
            8.9355341,
            50.037936101
          ],
          [
            8.9357656,
            50.037458401
          ],
          [
            8.9364268,
            50.036097601
          ],
          [
            8.9372439,
            50.034256201
          ],
          [
            8.9378327,
            50.032879801
          ],
          [
            8.9384554,
            50.031494501
          ],
          [
            8.9388368,
            50.030729201
          ],
          [
            8.9390736,
            50.030281401
          ],
          [
            8.9395267,
            50.029508801
          ],
          [
            8.9398908,
            50.028941201
          ],
          [
            8.940309,
            50.028351101
          ],
          [
            8.9407746,
            50.027767501
          ]
        ]
      }
    },
    {
      "identifier": "undefined--vi-hind.2025-08-13_10-21-39-000.f_004.de0",
      "icon": "101",
      "isBlocked": "false",
      "future": false,
      "extent": "50.06645708380128,8.83040833594486,50.05875164470893,8.887714621328172",
      "point": "50.06645708380128,8.83040833594486",
      "startLcPosition": "156",
      "display_type": "WARNING",
      "subtitle": " Frankfurt -> Würzburg",
      "title": "A3 | Obertshausen - Hanau",
      "startTimestamp": "2025-08-13T10:21:39+02:00",
      "coordinate": {
        "lat": 50.06645708380128,
        "long": 8.83040833594486
      },
      "description": [
        "Beginn: 13.08.25 um 10:21 Uhr",
        "",
        "Fahrzeug-Hindernis, seit 13.08.2025, 10:21",
        "A3: Frankfurt -> Würzburg, zwischen 0.3 km hinter AS Obertshausen und 0.3 km vor AS Hanau"
      ],
      "routeRecommendation": [],
      "footer": [],
      "lorryParkingFeatureIcons": [],
      "geometry": {
        "type": "LineString",
        "coordinates": [
          [
            8.830408336,
            50.066457084
          ],
          [
            8.8304451,
            50.066448201
          ],
          [
            8.830655,
            50.066400701
          ],
          [
            8.8308669,
            50.066348901
          ],
          [
            8.8320299,
            50.066064501
          ],
          [
            8.832538,
            50.065929501
          ],
          [
            8.8340194,
            50.065548301
          ],
          [
            8.8367555,
            50.064799101
          ],
          [
            8.8421549,
            50.063336901
          ],
          [
            8.8432549,
            50.063048201
          ],
          [
            8.8444079,
            50.062763301
          ],
          [
            8.845786,
            50.062444401
          ],
          [
            8.8471962,
            50.062139501
          ],
          [
            8.8481877,
            50.061944401
          ],
          [
            8.8492778,
            50.061755801
          ],
          [
            8.8503292,
            50.061592401
          ],
          [
            8.8512894,
            50.061458301
          ],
          [
            8.8525323,
            50.061309901
          ],
          [
            8.8537372,
            50.061181201
          ],
          [
            8.8549169,
            50.061070101
          ],
          [
            8.8561493,
            50.060969101
          ],
          [
            8.8572265,
            50.060894101
          ],
          [
            8.8583295,
            50.060819501
          ],
          [
            8.8606937,
            50.060663601
          ],
          [
            8.864734,
            50.060400601
          ],
          [
            8.8652064,
            50.060369901
          ],
          [
            8.8680138,
            50.060187001
          ],
          [
            8.8682711,
            50.060171501
          ],
          [
            8.8707543,
            50.060009801
          ],
          [
            8.8710622,
            50.059991601
          ],
          [
            8.8712355,
            50.059981001
          ],
          [
            8.8718662,
            50.059935801
          ],
          [
            8.8727205,
            50.059880201
          ],
          [
            8.8733623,
            50.059838401
          ],
          [
            8.8752695,
            50.059722301
          ],
          [
            8.8755291,
            50.059705101
          ],
          [
            8.8756432,
            50.059697901
          ],
          [
            8.8786485,
            50.059483401
          ],
          [
            8.8798153,
            50.059400101
          ],
          [
            8.8802029,
            50.059372501
          ],
          [
            8.8820992,
            50.059236401
          ],
          [
            8.8839983,
            50.059083401
          ],
          [
            8.8869958,
            50.058819301
          ],
          [
            8.887714621,
            50.058751645
          ]
        ]
      }
    },
    {
      "identifier": "undefined--vi-avl.2025-08-13_09-40-36-000.f_004.de0",
      "icon": "101",
      "isBlocked": "false",
      "future": false,
      "extent": "50.63170699042219,7.379944637158734,50.68658613118162,7.274472347986031",
      "point": "50.63170699042219,7.379944637158734",
      "startLcPosition": "196",
      "display_type": "WARNING",
      "subtitle": " Frankfurt -> Köln",
      "title": "A3 | Pfaffenbach - Bonn/Siegburg",
      "startTimestamp": "2025-08-13T09:40:36+02:00",
      "delayTimeValue": "32",
      "abnormalTrafficType": "STATIONARY_TRAFFIC",
      "averageSpeed": "16",
      "coordinate": {
        "lat": 50.63170699042219,
        "long": 7.379944637158734
      },
      "description": [
        "Beginn: 13.08.25 um 09:40 Uhr",
        "",
        "Angespannte Verkehrslage, seit 13.08.2025, 09:40",
        "A3: Frankfurt -> Köln, zwischen 3.2 km hinter Pfaffenbach und 11.0 km vor AK Bonn/Siegburg",
        "",
        "Im Stillstand",
        "Reisezeitverlust: 32 Minuten",
        "Durchschnittsgeschwindigkeit: 16 km/h"
      ],
      "routeRecommendation": [],
      "footer": [],
      "lorryParkingFeatureIcons": [],
      "geometry": {
        "type": "LineString",
        "coordinates": [
          [
            7.379944637,
            50.63170699
          ],
          [
            7.3798943,
            50.631736001
          ],
          [
            7.3790541,
            50.632146001
          ],
          [
            7.3782098,
            50.632532201
          ],
          [
            7.3772281,
            50.632909901
          ],
          [
            7.3763637,
            50.633188901
          ],
          [
            7.3755437,
            50.633430401
          ],
          [
            7.3745923,
            50.633670701
          ],
          [
            7.3718989,
            50.634222901
          ],
          [
            7.3670518,
            50.635206501
          ],
          [
            7.3596323,
            50.636723901
          ],
          [
            7.3570647,
            50.637241301
          ],
          [
            7.3557007,
            50.637526901
          ],
          [
            7.3544302,
            50.637815501
          ],
          [
            7.3534691,
            50.638057701
          ],
          [
            7.3526863,
            50.638281901
          ],
          [
            7.3517657,
            50.638565901
          ],
          [
            7.3506314,
            50.638955201
          ],
          [
            7.3497094,
            50.639307301
          ],
          [
            7.3486179,
            50.639752301
          ],
          [
            7.347815,
            50.640126201
          ],
          [
            7.3470318,
            50.640510601
          ],
          [
            7.3453815,
            50.641346901
          ],
          [
            7.3422149,
            50.642944301
          ],
          [
            7.3406302,
            50.643740601
          ],
          [
            7.3397503,
            50.644189601
          ],
          [
            7.3388578,
            50.644638501
          ],
          [
            7.3353245,
            50.646480801
          ],
          [
            7.3335064,
            50.647610801
          ],
          [
            7.3331571,
            50.647851301
          ],
          [
            7.3324804,
            50.648333101
          ],
          [
            7.3316432,
            50.648996401
          ],
          [
            7.3306188,
            50.649929301
          ],
          [
            7.3303494,
            50.650167801
          ],
          [
            7.3301359,
            50.650395001
          ],
          [
            7.329765,
            50.650823401
          ],
          [
            7.3273017,
            50.653627801
          ],
          [
            7.3255987,
            50.655622701
          ],
          [
            7.3253717,
            50.655885901
          ],
          [
            7.3248919,
            50.656457101
          ],
          [
            7.3225057,
            50.659243501
          ],
          [
            7.321323,
            50.660639601
          ],
          [
            7.3200523,
            50.662049201
          ],
          [
            7.3196595,
            50.662458101
          ],
          [
            7.3194222,
            50.662687301
          ],
          [
            7.3187866,
            50.663253701
          ],
          [
            7.3176015,
            50.664184401
          ],
          [
            7.3168248,
            50.664681401
          ],
          [
            7.3162244,
            50.665046201
          ],
          [
            7.3154848,
            50.665457501
          ],
          [
            7.314739,
            50.665830601
          ],
          [
            7.3139137,
            50.666222001
          ],
          [
            7.3135039,
            50.666393501
          ],
          [
            7.3130639,
            50.666564101
          ],
          [
            7.3097803,
            50.667810501
          ],
          [
            7.308138,
            50.668442801
          ],
          [
            7.3074451,
            50.668715401
          ],
          [
            7.3066139,
            50.669061701
          ],
          [
            7.3059099,
            50.669361701
          ],
          [
            7.3047073,
            50.669924201
          ],
          [
            7.303567,
            50.670552401
          ],
          [
            7.3025996,
            50.671161001
          ],
          [
            7.301563,
            50.671848101
          ],
          [
            7.3007131,
            50.672419701
          ],
          [
            7.2997489,
            50.673019101
          ],
          [
            7.299125,
            50.673393101
          ],
          [
            7.2987818,
            50.673589001
          ],
          [
            7.2982298,
            50.673876101
          ],
          [
            7.2979264,
            50.674015701
          ],
          [
            7.2973191,
            50.674279301
          ],
          [
            7.2968027,
            50.674480901
          ],
          [
            7.296295,
            50.674667901
          ],
          [
            7.2951022,
            50.675069301
          ],
          [
            7.2937819,
            50.675489801
          ],
          [
            7.2925378,
            50.675884901
          ],
          [
            7.2912702,
            50.676282101
          ],
          [
            7.2902019,
            50.676616801
          ],
          [
            7.2862931,
            50.677847801
          ],
          [
            7.2853428,
            50.678171301
          ],
          [
            7.28445,
            50.678513201
          ],
          [
            7.2837755,
            50.678790401
          ],
          [
            7.2831198,
            50.679083801
          ],
          [
            7.2824902,
            50.679399301
          ],
          [
            7.2818885,
            50.679735901
          ],
          [
            7.2813165,
            50.680092801
          ],
          [
            7.2807759,
            50.680468801
          ],
          [
            7.2802683,
            50.680862801
          ],
          [
            7.2797951,
            50.681273601
          ],
          [
            7.2764438,
            50.684618401
          ],
          [
            7.2759923,
            50.685069101
          ],
          [
            7.274472348,
            50.686586131
          ]
        ]
      }
    },
    {
      "identifier": "undefined--vi-avl.2025-08-13_09-44-16-000.f_014.de0",
      "icon": "101",
      "isBlocked": "false",
      "future": false,
      "extent": "50.63178632908799,7.379791165587976,50.63178632908799,7.379791165587976",
      "point": "50.63178632908799,7.379791165587976",
      "startLcPosition": "197",
      "display_type": "WARNING",
      "subtitle": " Frankfurt -> Köln",
      "title": "A3 | Hambitz - Hambitz",
      "startTimestamp": "2025-08-13T11:11:53+02:00",
      "abnormalTrafficType": "STATIONARY_TRAFFIC",
      "averageSpeed": "16",
      "coordinate": {
        "lat": 50.63178632908799,
        "long": 7.379791165587976
      },
      "description": [
        "Beginn: 13.08.25 um 11:11 Uhr",
        "",
        "Angespannte Verkehrslage, seit 13.08.2025, 11:11",
        "A3: Frankfurt -> Köln, 1.5 km vor Hambitz, aus Richtung Pfaffenbach",
        "",
        "Im Stillstand",
        "Durchschnittsgeschwindigkeit: 16 km/h"
      ],
      "routeRecommendation": [],
      "footer": [],
      "lorryParkingFeatureIcons": []
    },
    {
      "identifier": "undefined--vi-avl.2025-08-13_09-29-26-000.f_013.de0",
      "icon": "101",
      "isBlocked": "false",
      "future": false,
      "extent": "51.01729145184755,7.013177223856071,51.03410630182261,7.009495789073979",
      "point": "51.01729145184755,7.013177223856071",
      "startLcPosition": "212",
      "display_type": "WARNING",
      "subtitle": " Köln -> Oberhausen",
      "title": "A3 | Köln-Mülheim - Leverkusen",
      "startTimestamp": "2025-08-13T09:29:26+02:00",
      "delayTimeValue": "0",
      "abnormalTrafficType": "SLOW_TRAFFIC",
      "averageSpeed": "57",
      "coordinate": {
        "lat": 51.01729145184755,
        "long": 7.013177223856071
      },
      "description": [
        "Beginn: 13.08.25 um 09:29 Uhr",
        "",
        "Angespannte Verkehrslage, seit 13.08.2025, 09:29",
        "A3: Köln -> Oberhausen, zwischen 3.8 km hinter AS Köln-Mülheim und 0.9 km vor AK Leverkusen",
        "",
        "Langsamer Verkehr",
        "Reisezeitverlust: 0 Minuten",
        "Durchschnittsgeschwindigkeit: 57 km/h"
      ],
      "routeRecommendation": [],
      "footer": [],
      "lorryParkingFeatureIcons": [],
      "geometry": {
        "type": "LineString",
        "coordinates": [
          [
            7.013177224,
            51.017291452
          ],
          [
            7.0131048,
            51.017620101
          ],
          [
            7.0126993,
            51.019460701
          ],
          [
            7.0122882,
            51.021294301
          ],
          [
            7.0121333,
            51.022037501
          ],
          [
            7.0118083,
            51.023497001
          ],
          [
            7.0116172,
            51.024354901
          ],
          [
            7.0111736,
            51.026346701
          ],
          [
            7.0109775,
            51.027245301
          ],
          [
            7.0100579,
            51.031329601
          ],
          [
            7.0099962,
            51.031624701
          ],
          [
            7.0095269,
            51.033963801
          ],
          [
            7.009495789,
            51.034106302
          ]
        ]
      }
    },
    {
      "identifier": "undefined--vi-avl.2025-08-13_09-01-44-000.f.de0",
      "icon": "101",
      "isBlocked": "false",
      "future": false,
      "extent": "51.080462539919736,6.988407277741386,51.13192517096914,6.974013370494767",
      "point": "51.080462539919736,6.988407277741386",
      "startLcPosition": "215",
      "display_type": "WARNING",
      "subtitle": " Köln -> Oberhausen",
      "title": "A3 | Leverkusen-Opladen - Ohligser Heide",
      "startTimestamp": "2025-08-13T09:01:44+02:00",
      "delayTimeValue": "9",
      "abnormalTrafficType": "QUEUING_TRAFFIC",
      "averageSpeed": "28.299999237060547",
      "coordinate": {
        "lat": 51.080462539919736,
        "long": 6.988407277741386
      },
      "description": [
        "Beginn: 13.08.25 um 09:01 Uhr",
        "",
        "Angespannte Verkehrslage, seit 13.08.2025, 09:01",
        "A3: Köln -> Oberhausen, zwischen 2.8 km hinter AS Leverkusen-Opladen und 3.0 km vor Ohligser Heide",
        "",
        "Stockender Verkehr",
        "Reisezeitverlust: 9 Minuten",
        "Durchschnittsgeschwindigkeit: 28 km/h"
      ],
      "routeRecommendation": [],
      "footer": [],
      "lorryParkingFeatureIcons": [],
      "geometry": {
        "type": "LineString",
        "coordinates": [
          [
            6.988407278,
            51.08046254
          ],
          [
            6.9884172,
            51.080691601
          ],
          [
            6.9884572,
            51.081651801
          ],
          [
            6.9884808,
            51.082433401
          ],
          [
            6.9886766,
            51.087192001
          ],
          [
            6.9887,
            51.087761701
          ],
          [
            6.9886781,
            51.089455401
          ],
          [
            6.9886095,
            51.091106901
          ],
          [
            6.9885778,
            51.092111601
          ],
          [
            6.9885051,
            51.094412001
          ],
          [
            6.9884597,
            51.095827001
          ],
          [
            6.988377,
            51.098068401
          ],
          [
            6.9883333,
            51.099253401
          ],
          [
            6.98814,
            51.104492901
          ],
          [
            6.9881083,
            51.105366701
          ],
          [
            6.9880027,
            51.108151401
          ],
          [
            6.9880001,
            51.108218101
          ],
          [
            6.9878955,
            51.110157601
          ],
          [
            6.9878391,
            51.110559301
          ],
          [
            6.9877604,
            51.111068701
          ],
          [
            6.9876061,
            51.111743001
          ],
          [
            6.9875658,
            51.111919001
          ],
          [
            6.9873468,
            51.112648201
          ],
          [
            6.9870227,
            51.113484101
          ],
          [
            6.9867129,
            51.114233801
          ],
          [
            6.9862023,
            51.115173501
          ],
          [
            6.9859814,
            51.115536001
          ],
          [
            6.9858283,
            51.115779301
          ],
          [
            6.9855739,
            51.116152501
          ],
          [
            6.9851985,
            51.116661701
          ],
          [
            6.9850179,
            51.116892701
          ],
          [
            6.9847686,
            51.117201701
          ],
          [
            6.9843975,
            51.117631701
          ],
          [
            6.9840264,
            51.118038501
          ],
          [
            6.9836526,
            51.118423501
          ],
          [
            6.983401,
            51.118675201
          ],
          [
            6.9814946,
            51.120609301
          ],
          [
            6.9813145,
            51.120808601
          ],
          [
            6.9808866,
            51.121246301
          ],
          [
            6.9803515,
            51.121775101
          ],
          [
            6.9797098,
            51.122425701
          ],
          [
            6.979154,
            51.122985001
          ],
          [
            6.9782619,
            51.123932901
          ],
          [
            6.9773536,
            51.125004501
          ],
          [
            6.9770705,
            51.125382701
          ],
          [
            6.9766982,
            51.125901401
          ],
          [
            6.9758528,
            51.127295801
          ],
          [
            6.9754324,
            51.128154801
          ],
          [
            6.9751034,
            51.128986201
          ],
          [
            6.97401337,
            51.131925171
          ]
        ]
      }
    },
    {
      "identifier": "undefined--vi-avl.2025-08-13_11-04-06-000.f_006.de0",
      "icon": "101",
      "isBlocked": "false",
      "future": false,
      "extent": "51.08045355308115,6.988406888459088,51.08045355308115,6.988406888459088",
      "point": "51.08045355308115,6.988406888459088",
      "startLcPosition": "216",
      "display_type": "WARNING",
      "subtitle": " Köln -> Oberhausen",
      "title": "A3 | Reusrather Heide - Reusrather Heide",
      "startTimestamp": "2025-08-13T11:11:53+02:00",
      "abnormalTrafficType": "QUEUING_TRAFFIC",
      "averageSpeed": "15",
      "coordinate": {
        "lat": 51.08045355308115,
        "long": 6.988406888459088
      },
      "description": [
        "Beginn: 13.08.25 um 11:11 Uhr",
        "",
        "Angespannte Verkehrslage, seit 13.08.2025, 11:11",
        "A3: Köln -> Oberhausen, 0.5 km vor Reusrather Heide, aus Richtung Leverkusen-Opladen",
        "",
        "Stockender Verkehr",
        "Durchschnittsgeschwindigkeit: 15 km/h"
      ],
      "routeRecommendation": [],
      "footer": [],
      "lorryParkingFeatureIcons": []
    },
    {
      "identifier": "undefined--vi-avl.2025-08-13_07-00-32-000.f_004.de0",
      "icon": "101",
      "isBlocked": "false",
      "future": false,
      "extent": "51.41928068314607,6.797064680673937,51.45212031954327,6.798989690545907",
      "point": "51.41928068314607,6.797064680673937",
      "startLcPosition": "229",
      "display_type": "WARNING",
      "subtitle": " Köln -> Oberhausen",
      "title": "A3 | Duisburg-Wedau - Oberhausen-Lirich",
      "startTimestamp": "2025-08-13T07:00:32+02:00",
      "delayTimeValue": "5",
      "abnormalTrafficType": "QUEUING_TRAFFIC",
      "averageSpeed": "29.200000762939453",
      "coordinate": {
        "lat": 51.41928068314607,
        "long": 6.797064680673937
      },
      "description": [
        "Beginn: 13.08.25 um 07:00 Uhr",
        "",
        "Angespannte Verkehrslage, seit 13.08.2025, 07:00",
        "A3: Köln -> Oberhausen, zwischen 1.2 km hinter AS Duisburg-Wedau und 3.1 km vor AS Oberhausen-Lirich",
        "",
        "Stockender Verkehr",
        "Reisezeitverlust: 5 Minuten",
        "Durchschnittsgeschwindigkeit: 29 km/h"
      ],
      "routeRecommendation": [],
      "footer": [],
      "lorryParkingFeatureIcons": [],
      "geometry": {
        "type": "LineString",
        "coordinates": [
          [
            6.797064681,
            51.419280683
          ],
          [
            6.7970741,
            51.419743201
          ],
          [
            6.7971382,
            51.420150101
          ],
          [
            6.7972449,
            51.420643501
          ],
          [
            6.7973696,
            51.421044401
          ],
          [
            6.7975794,
            51.421527901
          ],
          [
            6.7978003,
            51.421952801
          ],
          [
            6.7980356,
            51.422321601
          ],
          [
            6.7982824,
            51.422672801
          ],
          [
            6.7986144,
            51.423068401
          ],
          [
            6.7990453,
            51.423516601
          ],
          [
            6.7994548,
            51.423873101
          ],
          [
            6.8003718,
            51.424632101
          ],
          [
            6.8016267,
            51.425668501
          ],
          [
            6.8034579,
            51.427142201
          ],
          [
            6.8052833,
            51.428622901
          ],
          [
            6.8060057,
            51.429227001
          ],
          [
            6.806604,
            51.429791801
          ],
          [
            6.8071795,
            51.430452401
          ],
          [
            6.8075131,
            51.430907901
          ],
          [
            6.8079458,
            51.431628101
          ],
          [
            6.808189,
            51.432164101
          ],
          [
            6.8084036,
            51.432774201
          ],
          [
            6.8085805,
            51.433440101
          ],
          [
            6.8086719,
            51.434291601
          ],
          [
            6.8086467,
            51.435011601
          ],
          [
            6.8085949,
            51.435294701
          ],
          [
            6.8085049,
            51.435783601
          ],
          [
            6.8083711,
            51.436255401
          ],
          [
            6.8081629,
            51.436791301
          ],
          [
            6.8076985,
            51.437558701
          ],
          [
            6.807328,
            51.438101401
          ],
          [
            6.8071266,
            51.438375401
          ],
          [
            6.8070113,
            51.438519201
          ],
          [
            6.806881,
            51.438678001
          ],
          [
            6.806723,
            51.438858201
          ],
          [
            6.8066157,
            51.438969401
          ],
          [
            6.806519,
            51.439073001
          ],
          [
            6.8062495,
            51.439343001
          ],
          [
            6.8060946,
            51.439491001
          ],
          [
            6.8059466,
            51.439625401
          ],
          [
            6.805758,
            51.439792801
          ],
          [
            6.8056145,
            51.439911901
          ],
          [
            6.8054663,
            51.440028701
          ],
          [
            6.8053236,
            51.440140101
          ],
          [
            6.8051512,
            51.440272201
          ],
          [
            6.8049782,
            51.440402601
          ],
          [
            6.8048131,
            51.440518001
          ],
          [
            6.8045644,
            51.440691401
          ],
          [
            6.8042756,
            51.440882001
          ],
          [
            6.804079,
            51.441019501
          ],
          [
            6.8038505,
            51.441160301
          ],
          [
            6.8034265,
            51.441427901
          ],
          [
            6.8031663,
            51.441593001
          ],
          [
            6.8029209,
            51.441741601
          ],
          [
            6.802526,
            51.441990101
          ],
          [
            6.8022966,
            51.442138901
          ],
          [
            6.8022128,
            51.442194001
          ],
          [
            6.8021213,
            51.442258901
          ],
          [
            6.8019895,
            51.442362901
          ],
          [
            6.8018189,
            51.442514801
          ],
          [
            6.8015197,
            51.442715401
          ],
          [
            6.8009287,
            51.443114001
          ],
          [
            6.8005072,
            51.443455601
          ],
          [
            6.8001702,
            51.443830301
          ],
          [
            6.7999821,
            51.444040501
          ],
          [
            6.799686,
            51.444432601
          ],
          [
            6.7994176,
            51.444873701
          ],
          [
            6.7991609,
            51.445441601
          ],
          [
            6.7989272,
            51.446131001
          ],
          [
            6.7988089,
            51.446649801
          ],
          [
            6.7986067,
            51.447956501
          ],
          [
            6.7985277,
            51.448754201
          ],
          [
            6.7985139,
            51.449179901
          ],
          [
            6.7985241,
            51.449640101
          ],
          [
            6.7985833,
            51.450163201
          ],
          [
            6.7987529,
            51.451060901
          ],
          [
            6.7988688,
            51.451579701
          ],
          [
            6.7989799,
            51.452084501
          ],
          [
            6.798989691,
            51.45212032
          ]
        ]
      }
    },
    {
      "identifier": "undefined--vi-avl.2025-08-13_11-09-14-000.f_018.de0",
      "icon": "101",
      "isBlocked": "false",
      "future": false,
      "extent": "51.41937955700932,6.79706669426754,51.41937955700932,6.79706669426754",
      "point": "51.41937955700932,6.79706669426754",
      "startLcPosition": "230",
      "display_type": "WARNING",
      "subtitle": " Köln -> Oberhausen",
      "title": "A3 | Kaiserberg - Kaiserberg",
      "startTimestamp": "2025-08-13T11:11:53+02:00",
      "abnormalTrafficType": "QUEUING_TRAFFIC",
      "averageSpeed": "23",
      "coordinate": {
        "lat": 51.41937955700932,
        "long": 6.79706669426754
      },
      "description": [
        "Beginn: 13.08.25 um 11:11 Uhr",
        "",
        "Angespannte Verkehrslage, seit 13.08.2025, 11:11",
        "A3: Köln -> Oberhausen, 3.4 km vor AK Kaiserberg, aus Richtung Duisburg-Wedau",
        "",
        "Stockender Verkehr",
        "Durchschnittsgeschwindigkeit: 23 km/h"
      ],
      "routeRecommendation": [],
      "footer": [],
      "lorryParkingFeatureIcons": []
    },
    {
      "identifier": "undefined--vi-avl.2025-08-13_11-11-53-000.f_013.de0",
      "icon": "101",
      "isBlocked": "false",
      "future": false,
      "extent": "51.45971628180116,6.80771009565481,51.45525885653129,6.800347957873949",
      "point": "51.45971628180116,6.80771009565481",
      "startLcPosition": "231",
      "display_type": "WARNING",
      "subtitle": " Oberhausen -> Köln",
      "title": "A3 | Oberhausen-Lirich - Kaiserberg",
      "startTimestamp": "2025-08-13T11:11:53+02:00",
      "delayTimeValue": "0",
      "abnormalTrafficType": "SLOW_TRAFFIC",
      "averageSpeed": "42.20000076293945",
      "coordinate": {
        "lat": 51.45971628180116,
        "long": 6.80771009565481
      },
      "description": [
        "Beginn: 13.08.25 um 11:11 Uhr",
        "",
        "Angespannte Verkehrslage, seit 13.08.2025, 11:11",
        "A3: Oberhausen -> Köln, zwischen 2.0 km hinter AS Oberhausen-Lirich und 1.0 km vor AK Kaiserberg",
        "",
        "Langsamer Verkehr",
        "Reisezeitverlust: 0 Minuten",
        "Durchschnittsgeschwindigkeit: 42 km/h"
      ],
      "routeRecommendation": [],
      "footer": [],
      "lorryParkingFeatureIcons": [],
      "geometry": {
        "type": "LineString",
        "coordinates": [
          [
            6.807710096,
            51.459716282
          ],
          [
            6.8060584,
            51.459152001
          ],
          [
            6.8051398,
            51.458783801
          ],
          [
            6.8041123,
            51.458291601
          ],
          [
            6.8035922,
            51.458006301
          ],
          [
            6.8032034,
            51.457767701
          ],
          [
            6.8026877,
            51.457432201
          ],
          [
            6.8022097,
            51.457083801
          ],
          [
            6.8015562,
            51.456559101
          ],
          [
            6.8011805,
            51.456212901
          ],
          [
            6.8007853,
            51.455802301
          ],
          [
            6.8005601,
            51.455544201
          ],
          [
            6.800347958,
            51.455258857
          ]
        ]
      }
    },
    {
      "identifier": "undefined--vi-avl.2025-08-13_06-04-00-000.f.de0",
      "icon": "101",
      "isBlocked": "false",
      "future": false,
      "extent": "51.49090613605023,6.8167400559635265,51.531595147465644,6.822441939876939",
      "point": "51.49090613605023,6.8167400559635265",
      "startLcPosition": "232",
      "display_type": "WARNING",
      "subtitle": " Köln -> Arnheim",
      "title": "A3 | Oberhausen-West - Oberhausen",
      "startTimestamp": "2025-08-13T06:04:00+02:00",
      "delayTimeValue": "5",
      "abnormalTrafficType": "QUEUING_TRAFFIC",
      "averageSpeed": "37.70000076293945",
      "coordinate": {
        "lat": 51.49090613605023,
        "long": 6.8167400559635265
      },
      "description": [
        "Beginn: 13.08.25 um 06:04 Uhr",
        "",
        "Angespannte Verkehrslage, seit 13.08.2025, 06:04",
        "A3: Köln -> Arnheim, zwischen 0.4 km hinter AK Oberhausen-West und 1.0 km vor AK Oberhausen",
        "",
        "Stockender Verkehr",
        "Reisezeitverlust: 5 Minuten",
        "Durchschnittsgeschwindigkeit: 37 km/h"
      ],
      "routeRecommendation": [],
      "footer": [],
      "lorryParkingFeatureIcons": [],
      "geometry": {
        "type": "LineString",
        "coordinates": [
          [
            6.816740056,
            51.490906136
          ],
          [
            6.8168475,
            51.491124901
          ],
          [
            6.8169379,
            51.491302401
          ],
          [
            6.8172877,
            51.492009101
          ],
          [
            6.8181676,
            51.493793301
          ],
          [
            6.8187383,
            51.494976001
          ],
          [
            6.8188377,
            51.495190101
          ],
          [
            6.8203338,
            51.498244801
          ],
          [
            6.8208302,
            51.499258301
          ],
          [
            6.8208897,
            51.499375001
          ],
          [
            6.8212857,
            51.500183001
          ],
          [
            6.8214095,
            51.500416701
          ],
          [
            6.8225454,
            51.502748801
          ],
          [
            6.8228404,
            51.503527401
          ],
          [
            6.8229282,
            51.503922701
          ],
          [
            6.8229922,
            51.504291501
          ],
          [
            6.8230288,
            51.504918601
          ],
          [
            6.8230301,
            51.505078801
          ],
          [
            6.8230282,
            51.505268601
          ],
          [
            6.8229753,
            51.505726001
          ],
          [
            6.8229084,
            51.506127601
          ],
          [
            6.822674,
            51.506872001
          ],
          [
            6.8226245,
            51.507014201
          ],
          [
            6.8223129,
            51.507628301
          ],
          [
            6.8220038,
            51.508124101
          ],
          [
            6.8217001,
            51.508534201
          ],
          [
            6.8213765,
            51.508934401
          ],
          [
            6.8213058,
            51.509025601
          ],
          [
            6.820424,
            51.510134801
          ],
          [
            6.8199409,
            51.510738901
          ],
          [
            6.8190335,
            51.511888201
          ],
          [
            6.8181518,
            51.513010801
          ],
          [
            6.8180335,
            51.513163701
          ],
          [
            6.817751,
            51.513503801
          ],
          [
            6.8171016,
            51.514294301
          ],
          [
            6.8167172,
            51.514796201
          ],
          [
            6.8164841,
            51.515107001
          ],
          [
            6.8162054,
            51.515495001
          ],
          [
            6.8158006,
            51.516109301
          ],
          [
            6.8155701,
            51.516491301
          ],
          [
            6.8152198,
            51.517174601
          ],
          [
            6.8149818,
            51.517686401
          ],
          [
            6.8148015,
            51.518139101
          ],
          [
            6.8146508,
            51.518613901
          ],
          [
            6.8145091,
            51.519154101
          ],
          [
            6.8144114,
            51.519685901
          ],
          [
            6.8143496,
            51.520143101
          ],
          [
            6.814327,
            51.520621601
          ],
          [
            6.8143339,
            51.521052301
          ],
          [
            6.8143747,
            51.521528201
          ],
          [
            6.8144323,
            51.521914201
          ],
          [
            6.8145512,
            51.522434601
          ],
          [
            6.8146345,
            51.522721501
          ],
          [
            6.8147656,
            51.523123401
          ],
          [
            6.8149696,
            51.523644101
          ],
          [
            6.8151965,
            51.524132601
          ],
          [
            6.8154525,
            51.524589201
          ],
          [
            6.8159646,
            51.525449301
          ],
          [
            6.8164466,
            51.526080301
          ],
          [
            6.8173036,
            51.527073701
          ],
          [
            6.8179931,
            51.527729701
          ],
          [
            6.8189694,
            51.528621701
          ],
          [
            6.8198401,
            51.529413701
          ],
          [
            6.820448,
            51.529961901
          ],
          [
            6.8205552,
            51.530053801
          ],
          [
            6.8210314,
            51.530467001
          ],
          [
            6.8212533,
            51.530668901
          ],
          [
            6.8220716,
            51.531321001
          ],
          [
            6.82244194,
            51.531595147
          ]
        ]
      }
    },
    {
      "identifier": "undefined--vi-avl.2025-08-13_10-57-18-000.f_009.de0",
      "icon": "101",
      "isBlocked": "false",
      "future": false,
      "extent": "51.56538138165448,6.804836086804314,51.592541509167916,6.782858317139362",
      "point": "51.56538138165448,6.804836086804314",
      "startLcPosition": "235",
      "display_type": "WARNING",
      "subtitle": " Oberhausen -> Arnheim",
      "title": "A3 | Dinslaken-Süd - Bergschlag",
      "startTimestamp": "2025-08-13T10:57:18+02:00",
      "delayTimeValue": "3",
      "abnormalTrafficType": "QUEUING_TRAFFIC",
      "averageSpeed": "39.900001525878906",
      "coordinate": {
        "lat": 51.56538138165448,
        "long": 6.804836086804314
      },
      "description": [
        "Beginn: 13.08.25 um 10:57 Uhr",
        "",
        "Angespannte Verkehrslage, seit 13.08.2025, 10:57",
        "A3: Oberhausen -> Arnheim, zwischen 0.7 km hinter AS Dinslaken-Süd und 1.9 km vor Bergschlag",
        "",
        "Stockender Verkehr",
        "Reisezeitverlust: 3 Minuten",
        "Durchschnittsgeschwindigkeit: 39 km/h"
      ],
      "routeRecommendation": [],
      "footer": [],
      "lorryParkingFeatureIcons": [],
      "geometry": {
        "type": "LineString",
        "coordinates": [
          [
            6.804836087,
            51.565381382
          ],
          [
            6.8046871,
            51.565630401
          ],
          [
            6.8025372,
            51.569238201
          ],
          [
            6.800834,
            51.571999601
          ],
          [
            6.8006626,
            51.572266101
          ],
          [
            6.7999169,
            51.573365201
          ],
          [
            6.7994931,
            51.573924501
          ],
          [
            6.7984538,
            51.575210901
          ],
          [
            6.7981022,
            51.575620501
          ],
          [
            6.7969304,
            51.576918101
          ],
          [
            6.7963472,
            51.577518501
          ],
          [
            6.7950966,
            51.578698501
          ],
          [
            6.7937978,
            51.579840001
          ],
          [
            6.7889822,
            51.583811201
          ],
          [
            6.7872684,
            51.585283701
          ],
          [
            6.7865318,
            51.585969801
          ],
          [
            6.7858743,
            51.586649201
          ],
          [
            6.7849615,
            51.587796301
          ],
          [
            6.784453,
            51.588550501
          ],
          [
            6.7840089,
            51.589299101
          ],
          [
            6.7836517,
            51.590010801
          ],
          [
            6.7833776,
            51.590656501
          ],
          [
            6.7832582,
            51.591039901
          ],
          [
            6.7830261,
            51.591819401
          ],
          [
            6.7828939,
            51.592363101
          ],
          [
            6.782858317,
            51.592541509
          ]
        ]
      }
    },
    {
      "identifier": "undefined--vi-avl.2025-08-13_11-09-52-000.f_010.de0",
      "icon": "101",
      "isBlocked": "false",
      "future": false,
      "extent": "51.56540664942092,6.804820969326157,51.56540664942092,6.804820969326157",
      "point": "51.56540664942092,6.804820969326157",
      "startLcPosition": "236",
      "display_type": "WARNING",
      "subtitle": " Oberhausen -> Arnheim",
      "title": "A3 | Sippenwies - Sippenwies",
      "startTimestamp": "2025-08-13T11:11:53+02:00",
      "abnormalTrafficType": "QUEUING_TRAFFIC",
      "averageSpeed": "18",
      "coordinate": {
        "lat": 51.56540664942092,
        "long": 6.804820969326157
      },
      "description": [
        "Beginn: 13.08.25 um 11:11 Uhr",
        "",
        "Angespannte Verkehrslage, seit 13.08.2025, 11:11",
        "A3: Oberhausen -> Arnheim, 1.5 km vor Sippenwies, aus Richtung Dinslaken-Süd",
        "",
        "Stockender Verkehr",
        "Durchschnittsgeschwindigkeit: 18 km/h"
      ],
      "routeRecommendation": [],
      "footer": [],
      "lorryParkingFeatureIcons": []
    },
    {
      "identifier": "undefined--vi-avl.2025-08-13_10-27-06-000.f_007.de0",
      "icon": "101",
      "isBlocked": "false",
      "future": false,
      "extent": "51.66613780093244,6.720571499994914,51.66613780093244,6.720571499994914",
      "point": "51.66613780093244,6.720571499994914",
      "startLcPosition": "240",
      "display_type": "WARNING",
      "subtitle": " Arnheim -> Oberhausen",
      "title": "A3 | Hünxe - Hünxe",
      "startTimestamp": "2025-08-13T11:11:53+02:00",
      "abnormalTrafficType": "STATIONARY_TRAFFIC",
      "averageSpeed": "19",
      "coordinate": {
        "lat": 51.66613780093244,
        "long": 6.720571499994914
      },
      "description": [
        "Beginn: 13.08.25 um 11:11 Uhr",
        "",
        "Angespannte Verkehrslage, seit 13.08.2025, 11:11",
        "A3: Arnheim -> Oberhausen, 3.1 km vor AS Hünxe, aus Richtung Wesel",
        "",
        "Im Stillstand",
        "Durchschnittsgeschwindigkeit: 19 km/h"
      ],
      "routeRecommendation": [],
      "footer": [],
      "lorryParkingFeatureIcons": []
    },
    {
      "identifier": "undefined--vi-avl.2025-08-13_09-15-42-000.f.de0",
      "icon": "101",
      "isBlocked": "false",
      "future": false,
      "extent": "51.66613780093244,6.720571499994914,51.622352822413085,6.760448244958786",
      "point": "51.66613780093244,6.720571499994914",
      "startLcPosition": "241",
      "display_type": "WARNING",
      "subtitle": " Arnheim -> Oberhausen",
      "title": "A3 | Wesel - Bergschlag",
      "startTimestamp": "2025-08-13T09:15:42+02:00",
      "delayTimeValue": "15",
      "abnormalTrafficType": "STATIONARY_TRAFFIC",
      "averageSpeed": "18.899999618530273",
      "coordinate": {
        "lat": 51.66613780093244,
        "long": 6.720571499994914
      },
      "description": [
        "Beginn: 13.08.25 um 09:15 Uhr",
        "",
        "Angespannte Verkehrslage, seit 13.08.2025, 09:15",
        "A3: Arnheim -> Oberhausen, zwischen 0.2 km hinter AS Wesel und 1.9 km vor Bergschlag",
        "",
        "Im Stillstand",
        "Reisezeitverlust: 15 Minuten",
        "Durchschnittsgeschwindigkeit: 18 km/h"
      ],
      "routeRecommendation": [],
      "footer": [],
      "lorryParkingFeatureIcons": [],
      "geometry": {
        "type": "LineString",
        "coordinates": [
          [
            6.7205715,
            51.666137801
          ],
          [
            6.7225728,
            51.664229101
          ],
          [
            6.7235164,
            51.663337601
          ],
          [
            6.7236832,
            51.663181401
          ],
          [
            6.7238942,
            51.662985801
          ],
          [
            6.7248804,
            51.662068001
          ],
          [
            6.7273786,
            51.659674801
          ],
          [
            6.7299458,
            51.657232401
          ],
          [
            6.7312308,
            51.656007801
          ],
          [
            6.73162,
            51.655641501
          ],
          [
            6.7325594,
            51.654745401
          ],
          [
            6.7340443,
            51.653323901
          ],
          [
            6.7350837,
            51.652287901
          ],
          [
            6.735921,
            51.651367501
          ],
          [
            6.7367589,
            51.650368601
          ],
          [
            6.7376117,
            51.649214501
          ],
          [
            6.7389216,
            51.647264101
          ],
          [
            6.739073,
            51.647032901
          ],
          [
            6.7407893,
            51.644259601
          ],
          [
            6.742308,
            51.641841601
          ],
          [
            6.7425599,
            51.641438401
          ],
          [
            6.7428802,
            51.640941101
          ],
          [
            6.7437669,
            51.639526901
          ],
          [
            6.744128,
            51.638950301
          ],
          [
            6.7455491,
            51.636646401
          ],
          [
            6.7463038,
            51.635438901
          ],
          [
            6.7470989,
            51.634301101
          ],
          [
            6.7479238,
            51.633171701
          ],
          [
            6.7490036,
            51.631914501
          ],
          [
            6.7501488,
            51.630697301
          ],
          [
            6.7512388,
            51.629673801
          ],
          [
            6.7518724,
            51.629116201
          ],
          [
            6.7530203,
            51.628171601
          ],
          [
            6.7541188,
            51.627299501
          ],
          [
            6.7563076,
            51.625595501
          ],
          [
            6.7566357,
            51.625333801
          ],
          [
            6.7568725,
            51.625142301
          ],
          [
            6.760448245,
            51.622352822
          ]
        ]
      }
    }
  ]
}
